m3_data_import/__init__.py
m3_data_import/ui.py
m3_data_import/utils.py
m3_data_import/actions/__init__.py
m3_data_import/actions/bulk.py
m3_data_import/templates/data-import-result-window.js
m3_data_import-2.2.0.dist-info/METADATA
m3_data_import-2.2.0.dist-info/WHEEL
m3_data_import-2.2.0.dist-info/dependency_links.txt
m3_data_import-2.2.0.dist-info/top_level.txt
m3_data_import-2.2.0.dist-info/RECORD
