Metadata-Version: 2.4
Name: m3-data-import
Version: 2.2.0
Summary: Пакет импорта данных - UI
Author: БАРС Груп
Author-email: dev@bars-open.ru
Classifier: Intended Audience :: Developers
Classifier: Natural Language :: Russian
Classifier: Operating System :: OS Independent
Classifier: Framework :: Django :: 2.2
Classifier: Framework :: Django :: 3.0
Classifier: Framework :: Django :: 3.1
Classifier: Framework :: Django :: 3.2
Classifier: Framework :: Django :: 4.0
Classifier: Framework :: Django :: 4.1
Classifier: Framework :: Django :: 4.2
Classifier: Programming Language :: Python
Classifier: Programming Language :: Python :: 3.7
Classifier: Programming Language :: Python :: 3.8
Classifier: Programming Language :: Python :: 3.9
Classifier: Programming Language :: Python :: Implementation :: CPython
Classifier: Development Status :: 5 - Production/Stable
Classifier: Topic :: Software Development
Requires-Dist: data-import<3,>=2.2
Requires-Dist: m3-core<2.3,>=2.2.29
Requires-Dist: m3-ui<2.3,>=2.2.31
Requires-Dist: m3-objectpack<2.5,>=2.3.1
Requires-Dist: Django<5,>=2.2
Dynamic: author
Dynamic: author-email
Dynamic: classifier
Dynamic: description
Dynamic: description-content-type
Dynamic: requires-dist
Dynamic: summary
